COPYING.AGPL-3
HACKING
INSTALL
MANIFEST.in
NEWS
README
setup-dev-env.sh
setup.cfg
setup.py
dashboard_app/__init__.py
dashboard_app/admin.py
dashboard_app/bread_crumbs.py
dashboard_app/extension.py
dashboard_app/filters.py
dashboard_app/helpers.py
dashboard_app/managers.py
dashboard_app/models.py
dashboard_app/patches.py
dashboard_app/signals.py
dashboard_app/urls.py
dashboard_app/xmlrpc.py
dashboard_app/fixtures/hacking_admin_user.json
dashboard_app/fixtures/hacking_gcc_bundle_stream.json
dashboard_app/fixtures/hacking_initial_bundle_stream.json
dashboard_app/fixtures/hacking_localhost_site.json
dashboard_app/fixtures/test_run_detail.json
dashboard_app/migrations/0001_initial.py
dashboard_app/migrations/0002_add_index_NamedAttribute_object_id_and_content_type_id_and_name.py
dashboard_app/migrations/0003_add_index_HardwareDevice_device_type.py
dashboard_app/migrations/0004_auto__add_softwarepackagescratch.py
dashboard_app/migrations/0005_auto__chg_field_softwarepackage_version__chg_field_softwarepackage_nam.py
dashboard_app/migrations/0006_auto__chg_field_bundledeserializationerror_bundle.py
dashboard_app/migrations/0007_auto__add_tag.py
dashboard_app/migrations/0008_auto__add_testingeffort.py
dashboard_app/migrations/0009_auto__add_testrundenormalization.py
dashboard_app/migrations/0010_denormalize_test_run.py
dashboard_app/migrations/0011_auto__chg_field_namedattribute_value__chg_field_namedattribute_name.py
dashboard_app/migrations/0012_auto__del_field_bundle_content__add_field_bundle__raw_content__add_fie.py
dashboard_app/migrations/0013_auto__chg_field_testcase_units__chg_field_testcase_test_case_id__chg_f.py
dashboard_app/migrations/0014_auto__add_imageset__add_image__add_imageattribute.py
dashboard_app/migrations/0015_auto__add_launchpadbug.py
dashboard_app/migrations/0016_auto__add_field_image_uploaded_by__chg_field_image_name.py
dashboard_app/migrations/0017_auto__add_testrunfilterattribute__add_testrunfilter__add_unique_testru.py
lava_dashboard.egg-info/PKG-INFO
lava_dashboard.egg-info/SOURCES.txt
lava_dashboard.egg-info/dependency_links.txt
lava_dashboard.egg-info/entry_points.txt
lava_dashboard.egg-info/not-zip-safe
lava_dashboard.egg-info/requires.txt
lava_dashboard.egg-info/top_level.txt